[
  {
    "kind": "t3",
    "data": {
      "approved_at_utc": null,
      "subreddit": "xkcd",
      "selftext": "[What If #100](https://what-if.xkcd.com/100/) (relevant part at the bottom)\n\n[IMDB link](https://www.imdb.com/search/keyword/?keywords=anglo-zanzibar-war)\n\nI can't tell what the movie actually is. They might have created it as well.",
      "author_fullname": "t2_17j4ie",
      "saved": false,
      "mod_reason_title": null,
      "gilded": 0,
      "clicked": false,
      "title": "Someone on IMDB has tagged the only film about the Anglo Zanzibar War with \"cell camera\" and \"stupid world record\" in accordance with What If #100.",
      "link_flair_richtext": [],
      "subreddit_name_prefixed": "r/xkcd",
      "hidden": false,
      "pwls": 6,
      "link_flair_css_class": null,
      "downs": 0,
      "thumbnail_height": null,
      "hide_score": false,
      "name": "t3_csxvx8",
      "quarantine": false,
      "link_flair_text_color": "dark",
      "author_flair_background_color": null,
      "subreddit_type": "public",
      "ups": 309,
      "total_awards_received": 0,
      "media_embed": {},
      "thumbnail_width": null,
      "author_flair_template_id": "92d60016-1f3f-11e4-9ce3-12313b0a9aea",
      "is_original_content": false,
      "user_reports": [],
      "secure_media": null,
      "is_reddit_media_domain": false,
      "is_meta": false,
      "category": null,
      "secure_media_embed": {},
      "link_flair_text": null,
      "can_mod_post": false,
      "score": 309,
      "approved_by": null,
      "thumbnail": "self",
      "edited": false,
      "author_flair_css_class": "brownhat",
      "author_flair_richtext": [],
      "gildings": {},
      "post_hint": "self",
      "content_categories": null,
      "is_self": true,
      "mod_note": null,
      "created": 1566332658,
      "link_flair_type": "text",
      "wls": 6,
      "banned_by": null,
      "author_flair_type": "text",
      "domain": "self.xkcd",
      "allow_live_comments": false,
      "selftext_html": "&lt;!-- SC_OFF --&gt;&lt;div class=\"md\"&gt;&lt;p&gt;&lt;a href=\"https://what-if.xkcd.com/100/\"&gt;What If #100&lt;/a&gt; (relevant part at the bottom)&lt;/p&gt;\n\n&lt;p&gt;&lt;a href=\"https://www.imdb.com/search/keyword/?keywords=anglo-zanzibar-war\"&gt;IMDB link&lt;/a&gt;&lt;/p&gt;\n\n&lt;p&gt;I can&amp;#39;t tell what the movie actually is. They might have created it as well.&lt;/p&gt;\n&lt;/div&gt;&lt;!-- SC_ON --&gt;",
      "likes": null,
      "suggested_sort": null,
      "banned_at_utc": null,
      "view_count": null,
      "archived": false,
      "no_follow": false,
      "is_crosspostable": false,
      "pinned": false,
      "over_18": false,
      "preview": {
        "images": [
          {
            "source": {
              "url": "https://external-preview.redd.it/mEDV48texKiDxtgRo1TM978FCrA-YtOzM2uR92eZd4E.jpg?auto=webp&amp;s=86a6d0bd4389d5aa7f27fb4814a90c594d6d9575",
              "width": 340,
              "height": 289
            },
            "resolutions": [
              {
                "url": "https://external-preview.redd.it/mEDV48texKiDxtgRo1TM978FCrA-YtOzM2uR92eZd4E.jpg?width=108&amp;crop=smart&amp;auto=webp&amp;s=43eb99090491a0d55e6e67a8f320ebfecd377bfa",
                "width": 108,
                "height": 91
              },
              {
                "url": "https://external-preview.redd.it/mEDV48texKiDxtgRo1TM978FCrA-YtOzM2uR92eZd4E.jpg?width=216&amp;crop=smart&amp;auto=webp&amp;s=57f9537cd3db8e74ec2de2c11d7511494e987cd3",
                "width": 216,
                "height": 183
              },
              {
                "url": "https://external-preview.redd.it/mEDV48texKiDxtgRo1TM978FCrA-YtOzM2uR92eZd4E.jpg?width=320&amp;crop=smart&amp;auto=webp&amp;s=a254a8fd2baab3c02360883746ae75ed93a72040",
                "width": 320,
                "height": 272
              }
            ],
            "variants": {},
            "id": "dEn3SVPNql8ObI82OA2wAIUYf-8fB-mVVlw59XTexGY"
          }
        ],
        "enabled": false
      },
      "all_awardings": [],
      "media_only": false,
      "can_gild": false,
      "spoiler": false,
      "locked": false,
      "author_flair_text": "Wait, brown hat? who is this guy?",
      "visited": false,
      "num_reports": null,
      "distinguished": null,
      "subreddit_id": "t5_2qh0z",
      "mod_reason_by": null,
      "removal_reason": null,
      "link_flair_background_color": "",
      "id": "csxvx8",
      "is_robot_indexable": true,
      "report_reasons": null,
      "author": "cowsrock1",
      "num_crossposts": 0,
      "num_comments": 9,
      "send_replies": true,
      "whitelist_status": "all_ads",
      "contest_mode": false,
      "mod_reports": [],
      "author_patreon_flair": false,
      "author_flair_text_color": "dark",
      "permalink": "/r/xkcd/comments/csxvx8/someone_on_imdb_has_tagged_the_only_film_about/",
      "parent_whitelist_status": "all_ads",
      "stickied": false,
      "url": "https://www.reddit.com/r/xkcd/comments/csxvx8/someone_on_imdb_has_tagged_the_only_film_about/",
      "subreddit_subscribers": 123562,
      "created_utc": 1566303858,
      "discussion_type": null,
      "media": null,
      "is_video": false
    }
  },
  {
    "kind": "t3",
    "data": {
      "approved_at_utc": null,
      "subreddit": "xkcd",
      "selftext": "",
      "author_fullname": "t2_ck1a946",
      "saved": false,
      "mod_reason_title": null,
      "gilded": 0,
      "clicked": false,
      "title": "Do What Ifs count?",
      "link_flair_richtext": [],
      "subreddit_name_prefixed": "r/xkcd",
      "hidden": false,
      "pwls": 6,
      "link_flair_css_class": null,
      "downs": 0,
      "thumbnail_height": null,
      "hide_score": false,
      "name": "t3_cst7jy",
      "quarantine": false,
      "link_flair_text_color": "dark",
      "author_flair_background_color": null,
      "subreddit_type": "public",
      "ups": 3,
      "total_awards_received": 0,
      "media_embed": {},
      "thumbnail_width": null,
      "author_flair_template_id": null,
      "is_original_content": false,
      "user_reports": [],
      "secure_media": null,
      "is_reddit_media_domain": false,
      "is_meta": false,
      "category": null,
      "secure_media_embed": {},
      "link_flair_text": null,
      "can_mod_post": false,
      "score": 3,
      "approved_by": null,
      "thumbnail": "default",
      "edited": false,
      "author_flair_css_class": null,
      "author_flair_richtext": [],
      "gildings": {},
      "content_categories": null,
      "is_self": false,
      "mod_note": null,
      "crosspost_parent_list": [
        {
          "approved_at_utc": null,
          "subreddit": "NoStupidQuestions",
          "selftext": "",
          "author_fullname": "t2_2yimycl1",
          "saved": false,
          "mod_reason_title": null,
          "gilded": 0,
          "clicked": false,
          "title": "If everyone in the world quarantined themselves for two weeks or so, would the common cold just cease to exist?",
          "link_flair_richtext": [],
          "subreddit_name_prefixed": "r/NoStupidQuestions",
          "hidden": false,
          "pwls": 6,
          "link_flair_css_class": null,
          "downs": 0,
          "thumbnail_height": null,
          "hide_score": false,
          "name": "t3_csipi8",
          "quarantine": false,
          "link_flair_text_color": "dark",
          "author_flair_background_color": null,
          "subreddit_type": "public",
          "ups": 6521,
          "total_awards_received": 0,
          "media_embed": {},
          "thumbnail_width": null,
          "author_flair_template_id": null,
          "is_original_content": false,
          "user_reports": [],
          "secure_media": null,
          "is_reddit_media_domain": false,
          "is_meta": false,
          "category": null,
          "secure_media_embed": {},
          "link_flair_text": null,
          "can_mod_post": false,
          "score": 6521,
          "approved_by": null,
          "thumbnail": "self",
          "edited": false,
          "author_flair_css_class": null,
          "author_flair_richtext": [],
          "gildings": {},
          "content_categories": null,
          "is_self": true,
          "mod_note": null,
          "created": 1566257742,
          "link_flair_type": "text",
          "wls": 6,
          "banned_by": null,
          "author_flair_type": "text",
          "domain": "self.NoStupidQuestions",
          "allow_live_comments": true,
          "selftext_html": null,
          "likes": null,
          "suggested_sort": null,
          "banned_at_utc": null,
          "view_count": null,
          "archived": false,
          "no_follow": false,
          "is_crosspostable": false,
          "pinned": false,
          "over_18": false,
          "all_awardings": [],
          "media_only": false,
          "can_gild": false,
          "spoiler": false,
          "locked": false,
          "author_flair_text": null,
          "visited": false,
          "num_reports": null,
          "distinguished": null,
          "subreddit_id": "t5_2w844",
          "mod_reason_by": null,
          "removal_reason": null,
          "link_flair_background_color": "",
          "id": "csipi8",
          "is_robot_indexable": true,
          "report_reasons": null,
          "author": "ImFairlyUnsure",
          "num_crossposts": 1,
          "num_comments": 421,
          "send_replies": true,
          "whitelist_status": "all_ads",
          "contest_mode": false,
          "mod_reports": [],
          "author_patreon_flair": false,
          "author_flair_text_color": null,
          "permalink": "/r/NoStupidQuestions/comments/csipi8/if_everyone_in_the_world_quarantined_themselves/",
          "parent_whitelist_status": "all_ads",
          "stickied": false,
          "url": "https://www.reddit.com/r/NoStupidQuestions/comments/csipi8/if_everyone_in_the_world_quarantined_themselves/",
          "subreddit_subscribers": 1171858,
          "created_utc": 1566228942,
          "discussion_type": null,
          "media": null,
          "is_video": false
        }
      ],
      "created": 1566309083,
      "link_flair_type": "text",
      "wls": 6,
      "banned_by": null,
      "author_flair_type": "text",
      "domain": "self.NoStupidQuestions",
      "allow_live_comments": false,
      "selftext_html": null,
      "likes": null,
      "suggested_sort": null,
      "banned_at_utc": null,
      "view_count": null,
      "archived": false,
      "no_follow": false,
      "is_crosspostable": false,
      "pinned": false,
      "over_18": false,
      "all_awardings": [],
      "media_only": false,
      "can_gild": false,
      "spoiler": false,
      "locked": false,
      "author_flair_text": null,
      "visited": false,
      "num_reports": null,
      "distinguished": null,
      "subreddit_id": "t5_2qh0z",
      "mod_reason_by": null,
      "removal_reason": null,
      "link_flair_background_color": "",
      "id": "cst7jy",
      "is_robot_indexable": true,
      "stickied": false,
      "author": "WeranioRacker",
      "num_crossposts": 0,
      "num_comments": 0,
      "send_replies": true,
      "whitelist_status": "all_ads",
      "contest_mode": false,
      "mod_reports": [],
      "author_patreon_flair": false,
      "crosspost_parent": "t3_csipi8",
      "author_flair_text_color": null,
      "permalink": "/r/xkcd/comments/cst7jy/do_what_ifs_count/",
      "parent_whitelist_status": "all_ads",
      "report_reasons": null,
      "url": "https://www.reddit.com/r/NoStupidQuestions/comments/csipi8/if_everyone_in_the_world_quarantined_themselves/",
      "subreddit_subscribers": 123562,
      "created_utc": 1566280283,
      "discussion_type": null,
      "media": null,
      "is_video": false
    }
  },
  {
    "kind": "t3",
    "data": {
      "approved_at_utc": null,
      "subreddit": "xkcd",
      "selftext": "",
      "author_fullname": "t2_4a27h",
      "saved": false,
      "mod_reason_title": null,
      "gilded": 0,
      "clicked": false,
      "title": "XKCD 2191: Conference Question",
      "link_flair_richtext": [],
      "subreddit_name_prefixed": "r/xkcd",
      "hidden": false,
      "pwls": 6,
      "link_flair_css_class": "xkcd",
      "downs": 0,
      "thumbnail_height": 140,
      "hide_score": false,
      "name": "t3_csbwv5",
      "quarantine": false,
      "link_flair_text_color": "dark",
      "author_flair_background_color": "",
      "subreddit_type": "public",
      "ups": 425,
      "total_awards_received": 0,
      "media_embed": {},
      "thumbnail_width": 140,
      "author_flair_template_id": null,
      "is_original_content": false,
      "user_reports": [],
      "secure_media": null,
      "is_reddit_media_domain": false,
      "is_meta": false,
      "category": null,
      "secure_media_embed": {},
      "link_flair_text": "XKCD",
      "can_mod_post": false,
      "score": 425,
      "approved_by": null,
      "thumbnail": "https://b.thumbs.redditmedia.com/ROkI-nHp_A8BMrGbnXQefH3pmf8Oixy9NII_WGOQfaI.jpg",
      "author_cakeday": true,
      "edited": false,
      "author_flair_css_class": "plain",
      "author_flair_richtext": [],
      "gildings": {},
      "post_hint": "link",
      "content_categories": null,
      "is_self": false,
      "mod_note": null,
      "created": 1566216377,
      "link_flair_type": "text",
      "wls": 6,
      "banned_by": null,
      "author_flair_type": "text",
      "domain": "xkcd.com",
      "allow_live_comments": false,
      "selftext_html": null,
      "likes": null,
      "suggested_sort": null,
      "banned_at_utc": null,
      "view_count": null,
      "archived": false,
      "no_follow": false,
      "is_crosspostable": false,
      "pinned": false,
      "over_18": false,
      "preview": {
        "images": [
          {
            "source": {
              "url": "https://external-preview.redd.it/wsLuW9P9eJHKOR3LAKxgLvVCAfM7OWHwHvut0nOfpoE.jpg?auto=webp&amp;s=3d1c114d0251eeb231b291bd71c12f8cde231043",
              "width": 559,
              "height": 954
            },
            "resolutions": [
              {
                "url": "https://external-preview.redd.it/wsLuW9P9eJHKOR3LAKxgLvVCAfM7OWHwHvut0nOfpoE.jpg?width=108&amp;crop=smart&amp;auto=webp&amp;s=9e3a7dfad9cefb989f74aa3f08c77715fa5caa51",
                "width": 108,
                "height": 184
              },
              {
                "url": "https://external-preview.redd.it/wsLuW9P9eJHKOR3LAKxgLvVCAfM7OWHwHvut0nOfpoE.jpg?width=216&amp;crop=smart&amp;auto=webp&amp;s=71bda1ce687df976e574880db11ff880d43c9ff3",
                "width": 216,
                "height": 368
              },
              {
                "url": "https://external-preview.redd.it/wsLuW9P9eJHKOR3LAKxgLvVCAfM7OWHwHvut0nOfpoE.jpg?width=320&amp;crop=smart&amp;auto=webp&amp;s=17a63daa188b04b70c2b0b47fa9f1ce660c1959d",
                "width": 320,
                "height": 546
              }
            ],
            "variants": {},
            "id": "JcMfH7niO2ZVMUqZpzAqGd5tGTvT1fnIesK4PC4dW9o"
          }
        ],
        "enabled": false
      },
      "all_awardings": [],
      "media_only": false,
      "can_gild": false,
      "spoiler": false,
      "locked": false,
      "author_flair_text": "A XKCD Addict",
      "visited": false,
      "num_reports": null,
      "distinguished": null,
      "subreddit_id": "t5_2qh0z",
      "mod_reason_by": null,
      "removal_reason": null,
      "link_flair_background_color": "",
      "id": "csbwv5",
      "is_robot_indexable": true,
      "report_reasons": null,
      "author": "antdude",
      "num_crossposts": 0,
      "num_comments": 32,
      "send_replies": false,
      "whitelist_status": "all_ads",
      "contest_mode": false,
      "mod_reports": [],
      "author_patreon_flair": false,
      "author_flair_text_color": "dark",
      "permalink": "/r/xkcd/comments/csbwv5/xkcd_2191_conference_question/",
      "parent_whitelist_status": "all_ads",
      "stickied": false,
      "url": "https://xkcd.com/2191/",
      "subreddit_subscribers": 123562,
      "created_utc": 1566187577,
      "discussion_type": null,
      "media": null,
      "is_video": false
    }
  },
  {
    "kind": "t3",
    "data": {
      "approved_at_utc": null,
      "subreddit": "xkcd",
      "selftext": "",
      "author_fullname": "t2_n9xfvry",
      "saved": false,
      "mod_reason_title": null,
      "gilded": 0,
      "clicked": false,
      "title": "1262: this one got me thinking (last Star Wars quote)",
      "link_flair_richtext": [],
      "subreddit_name_prefixed": "r/xkcd",
      "hidden": false,
      "pwls": 6,
      "link_flair_css_class": null,
      "downs": 0,
      "thumbnail_height": 140,
      "hide_score": false,
      "name": "t3_cs0dz6",
      "quarantine": false,
      "link_flair_text_color": "dark",
      "author_flair_background_color": null,
      "subreddit_type": "public",
      "ups": 1655,
      "total_awards_received": 0,
      "media_embed": {},
      "thumbnail_width": 140,
      "author_flair_template_id": null,
      "is_original_content": false,
      "user_reports": [],
      "secure_media": null,
      "is_reddit_media_domain": false,
      "is_meta": false,
      "category": null,
      "secure_media_embed": {},
      "link_flair_text": null,
      "can_mod_post": false,
      "score": 1655,
      "approved_by": null,
      "thumbnail": "https://b.thumbs.redditmedia.com/Gbv72dk8ntmycPehSfeOqtSyPvnmqgJsilvJi8brSWY.jpg",
      "edited": false,
      "author_flair_css_class": null,
      "author_flair_richtext": [],
      "gildings": {},
      "post_hint": "image",
      "content_categories": null,
      "is_self": false,
      "mod_note": null,
      "created": 1566158633,
      "link_flair_type": "text",
      "wls": 6,
      "banned_by": null,
      "author_flair_type": "text",
      "domain": "imgs.xkcd.com",
      "allow_live_comments": true,
      "selftext_html": null,
      "likes": null,
      "suggested_sort": null,
      "banned_at_utc": null,
      "view_count": null,
      "archived": false,
      "no_follow": false,
      "is_crosspostable": false,
      "pinned": false,
      "over_18": false,
      "preview": {
        "images": [
          {
            "source": {
              "url": "https://external-preview.redd.it/RofttCGcFkT4w52pGTANHyDqa17wc1EKAVEcoBw2Jjs.png?auto=webp&amp;s=35fdbde9981a7b384c4cbc268cf35f5b475d1e2f",
              "width": 583,
              "height": 773
            },
            "resolutions": [
              {
                "url": "https://external-preview.redd.it/RofttCGcFkT4w52pGTANHyDqa17wc1EKAVEcoBw2Jjs.png?width=108&amp;crop=smart&amp;auto=webp&amp;s=05020b429de9b9ae98fd055a1468a642339689aa",
                "width": 108,
                "height": 143
              },
              {
                "url": "https://external-preview.redd.it/RofttCGcFkT4w52pGTANHyDqa17wc1EKAVEcoBw2Jjs.png?width=216&amp;crop=smart&amp;auto=webp&amp;s=7f81a5feb3df9a2681294dca5b6b2461e7204960",
                "width": 216,
                "height": 286
              },
              {
                "url": "https://external-preview.redd.it/RofttCGcFkT4w52pGTANHyDqa17wc1EKAVEcoBw2Jjs.png?width=320&amp;crop=smart&amp;auto=webp&amp;s=d1566d3856b5227cbaed26f12191173f371a0b88",
                "width": 320,
                "height": 424
              }
            ],
            "variants": {},
            "id": "dhCKR-dUkdabwdyGaefeM0GfFtWWYx63GDEDiqn4S5E"
          }
        ],
        "enabled": true
      },
      "all_awardings": [],
      "media_only": false,
      "can_gild": false,
      "spoiler": false,
      "locked": false,
      "author_flair_text": null,
      "visited": false,
      "num_reports": null,
      "distinguished": null,
      "subreddit_id": "t5_2qh0z",
      "mod_reason_by": null,
      "removal_reason": null,
      "link_flair_background_color": "",
      "id": "cs0dz6",
      "is_robot_indexable": true,
      "report_reasons": null,
      "author": "verytigolbitties",
      "num_crossposts": 0,
      "num_comments": 75,
      "send_replies": true,
      "whitelist_status": "all_ads",
      "contest_mode": false,
      "mod_reports": [],
      "author_patreon_flair": false,
      "author_flair_text_color": null,
      "permalink": "/r/xkcd/comments/cs0dz6/1262_this_one_got_me_thinking_last_star_wars_quote/",
      "parent_whitelist_status": "all_ads",
      "stickied": false,
      "url": "https://imgs.xkcd.com/comics/unquote_2x.png",
      "subreddit_subscribers": 123562,
      "created_utc": 1566129833,
      "discussion_type": null,
      "media": null,
      "is_video": false
    }
  },
  {
    "kind": "t3",
    "data": {
      "approved_at_utc": null,
      "subreddit": "xkcd",
      "selftext": "",
      "author_fullname": "t2_6g18b",
      "saved": false,
      "mod_reason_title": null,
      "gilded": 0,
      "clicked": false,
      "title": "GIF of that tennis-on-drone violence video (XKCD 2190)",
      "link_flair_richtext": [],
      "subreddit_name_prefixed": "r/xkcd",
      "hidden": false,
      "pwls": 6,
      "link_flair_css_class": null,
      "downs": 0,
      "thumbnail_height": 79,
      "hide_score": false,
      "name": "t3_crpo1q",
      "quarantine": false,
      "link_flair_text_color": "dark",
      "author_flair_background_color": "",
      "subreddit_type": "public",
      "ups": 358,
      "total_awards_received": 0,
      "media_embed": {},
      "thumbnail_width": 140,
      "author_flair_template_id": null,
      "is_original_content": false,
      "user_reports": [],
      "secure_media": null,
      "is_reddit_media_domain": true,
      "is_meta": false,
      "category": null,
      "secure_media_embed": {},
      "link_flair_text": null,
      "can_mod_post": false,
      "score": 358,
      "approved_by": null,
      "thumbnail": "https://b.thumbs.redditmedia.com/zmmP1Tc0KB2u29qZUy5xl1HXKJGpm9bEtt8B3EbXu2o.jpg",
      "edited": false,
      "author_flair_css_class": "whitehat",
      "author_flair_richtext": [],
      "gildings": {},
      "post_hint": "image",
      "content_categories": null,
      "is_self": false,
      "mod_note": null,
      "created": 1566094028,
      "link_flair_type": "text",
      "wls": 6,
      "banned_by": null,
      "author_flair_type": "text",
      "domain": "i.redd.it",
      "allow_live_comments": false,
      "selftext_html": null,
      "likes": null,
      "suggested_sort": null,
      "banned_at_utc": null,
      "view_count": null,
      "archived": false,
      "no_follow": false,
      "is_crosspostable": false,
      "pinned": false,
      "over_18": false,
      "preview": {
        "images": [
          {
            "source": {
              "url": "https://preview.redd.it/zsyibsfeu1h31.gif?format=png8&amp;s=481a0bb52a0d7bc407690f17eb7d4cd281117e23",
              "width": 600,
              "height": 339
            },
            "resolutions": [
              {
                "url": "https://preview.redd.it/zsyibsfeu1h31.gif?width=108&amp;crop=smart&amp;format=png8&amp;s=581d4cd084d47d881313a5e1ad3e0185874a5708",
                "width": 108,
                "height": 61
              },
              {
                "url": "https://preview.redd.it/zsyibsfeu1h31.gif?width=216&amp;crop=smart&amp;format=png8&amp;s=7cbe63a29ab6e4701352934e3b69e39b35b0621a",
                "width": 216,
                "height": 122
              },
              {
                "url": "https://preview.redd.it/zsyibsfeu1h31.gif?width=320&amp;crop=smart&amp;format=png8&amp;s=ba8ce2f31cd106dfa6f5169e336163d795278948",
                "width": 320,
                "height": 180
              }
            ],
            "variants": {
              "gif": {
                "source": {
                  "url": "https://preview.redd.it/zsyibsfeu1h31.gif?s=172173d90e4111e38a5cb2392d7acb700eb1a1f4",
                  "width": 600,
                  "height": 339
                },
                "resolutions": [
                  {
                    "url": "https://preview.redd.it/zsyibsfeu1h31.gif?width=108&amp;crop=smart&amp;s=799c67ee8aaec8b4ca3054c335196cc62e1333ee",
                    "width": 108,
                    "height": 61
                  },
                  {
                    "url": "https://preview.redd.it/zsyibsfeu1h31.gif?width=216&amp;crop=smart&amp;s=0436118018de4b23447af20247f68866adb7ccc6",
                    "width": 216,
                    "height": 122
                  },
                  {
                    "url": "https://preview.redd.it/zsyibsfeu1h31.gif?width=320&amp;crop=smart&amp;s=26fe57195f5f97b10eebed1ad89d744960148b79",
                    "width": 320,
                    "height": 180
                  }
                ]
              },
              "mp4": {
                "source": {
                  "url": "https://preview.redd.it/zsyibsfeu1h31.gif?format=mp4&amp;s=b45e4ab33788ff27d51523c42970ba6f031d94e3",
                  "width": 600,
                  "height": 339
                },
                "resolutions": [
                  {
                    "url": "https://preview.redd.it/zsyibsfeu1h31.gif?width=108&amp;format=mp4&amp;s=4a1de6a1dd0c502355e5f2dbae53a90bc654e09e",
                    "width": 108,
                    "height": 61
                  },
                  {
                    "url": "https://preview.redd.it/zsyibsfeu1h31.gif?width=216&amp;format=mp4&amp;s=72c10805a35179036786a6bccbccdac64ff0f760",
                    "width": 216,
                    "height": 122
                  },
                  {
                    "url": "https://preview.redd.it/zsyibsfeu1h31.gif?width=320&amp;format=mp4&amp;s=ab54847da7cdb9740108ecc471142c0802fa3558",
                    "width": 320,
                    "height": 180
                  }
                ]
              }
            },
            "id": "HNB8OegjTTXVzU5oH4vx8VnB0TaTvbkx-POr49gaLLk"
          }
        ],
        "enabled": true
      },
      "all_awardings": [],
      "media_only": false,
      "can_gild": false,
      "spoiler": false,
      "locked": false,
      "author_flair_text": "White Hat",
      "visited": false,
      "num_reports": null,
      "distinguished": null,
      "subreddit_id": "t5_2qh0z",
      "mod_reason_by": null,
      "removal_reason": null,
      "link_flair_background_color": "",
      "id": "crpo1q",
      "is_robot_indexable": true,
      "report_reasons": null,
      "author": "avataRJ",
      "num_crossposts": 0,
      "num_comments": 11,
      "send_replies": true,
      "whitelist_status": "all_ads",
      "contest_mode": false,
      "mod_reports": [],
      "author_patreon_flair": false,
      "author_flair_text_color": "dark",
      "permalink": "/r/xkcd/comments/crpo1q/gif_of_that_tennisondrone_violence_video_xkcd_2190/",
      "parent_whitelist_status": "all_ads",
      "stickied": false,
      "url": "https://i.redd.it/zsyibsfeu1h31.gif",
      "subreddit_subscribers": 123562,
      "created_utc": 1566065228,
      "discussion_type": null,
      "media": null,
      "is_video": false
    }
  },
  {
    "kind": "t3",
    "data": {
      "approved_at_utc": null,
      "subreddit": "xkcd",
      "selftext": "",
      "author_fullname": "t2_5vpsm",
      "saved": false,
      "mod_reason_title": null,
      "gilded": 0,
      "clicked": false,
      "title": "Video of Serena Williams knocking down a drone with a Tennis Ball (xkcd 2190)",
      "link_flair_richtext": [],
      "subreddit_name_prefixed": "r/xkcd",
      "hidden": false,
      "pwls": 6,
      "link_flair_css_class": null,
      "downs": 0,
      "thumbnail_height": 140,
      "hide_score": false,
      "name": "t3_cromff",
      "quarantine": false,
      "link_flair_text_color": "dark",
      "author_flair_background_color": "",
      "subreddit_type": "public",
      "ups": 221,
      "total_awards_received": 0,
      "media_embed": {},
      "thumbnail_width": 140,
      "author_flair_template_id": null,
      "is_original_content": false,
      "user_reports": [],
      "secure_media": null,
      "is_reddit_media_domain": false,
      "is_meta": false,
      "category": null,
      "secure_media_embed": {},
      "link_flair_text": null,
      "can_mod_post": false,
      "score": 221,
      "approved_by": null,
      "thumbnail": "https://b.thumbs.redditmedia.com/I23X_DmNPPuEmeLi0Dm55j95hxURy5pfAdLRhbQ3EMo.jpg",
      "edited": false,
      "author_flair_css_class": "beret",
      "author_flair_richtext": [],
      "gildings": {},
      "post_hint": "link",
      "content_categories": null,
      "is_self": false,
      "mod_note": null,
      "created": 1566089398,
      "link_flair_type": "text",
      "wls": 6,
      "banned_by": null,
      "author_flair_type": "text",
      "domain": "facebook.com",
      "allow_live_comments": false,
      "selftext_html": null,
      "likes": null,
      "suggested_sort": null,
      "banned_at_utc": null,
      "view_count": null,
      "archived": false,
      "no_follow": false,
      "is_crosspostable": false,
      "pinned": false,
      "over_18": false,
      "preview": {
        "images": [
          {
            "source": {
              "url": "https://external-preview.redd.it/HbArelSSIlbbQH75d10W1o3mO5ntADmlU80SNmGDP5o.jpg?auto=webp&amp;s=8efd6960ba8e172eb6870ca78088b3836db2141c",
              "width": 442,
              "height": 442
            },
            "resolutions": [
              {
                "url": "https://external-preview.redd.it/HbArelSSIlbbQH75d10W1o3mO5ntADmlU80SNmGDP5o.jpg?width=108&amp;crop=smart&amp;auto=webp&amp;s=56e8bcd4e185683fa7bccb5fd7e5eb28cd4fd9ec",
                "width": 108,
                "height": 108
              },
              {
                "url": "https://external-preview.redd.it/HbArelSSIlbbQH75d10W1o3mO5ntADmlU80SNmGDP5o.jpg?width=216&amp;crop=smart&amp;auto=webp&amp;s=2005a843977b80f8bac92db8b66178c037137f73",
                "width": 216,
                "height": 216
              },
              {
                "url": "https://external-preview.redd.it/HbArelSSIlbbQH75d10W1o3mO5ntADmlU80SNmGDP5o.jpg?width=320&amp;crop=smart&amp;auto=webp&amp;s=088e573fbacfd007d6c8f3d4758676f3ed3ba1a7",
                "width": 320,
                "height": 320
              }
            ],
            "variants": {},
            "id": "6z4QPTlSJenPX13xRKB1or-OBj49fIzlTFhkU0SiTYg"
          }
        ],
        "enabled": false
      },
      "all_awardings": [],
      "media_only": false,
      "can_gild": false,
      "spoiler": false,
      "locked": false,
      "author_flair_text": "SCONES",
      "visited": false,
      "num_reports": null,
      "distinguished": null,
      "subreddit_id": "t5_2qh0z",
      "mod_reason_by": null,
      "removal_reason": null,
      "link_flair_background_color": "",
      "id": "cromff",
      "is_robot_indexable": true,
      "report_reasons": null,
      "author": "ryzvonusef",
      "num_crossposts": 0,
      "num_comments": 21,
      "send_replies": true,
      "whitelist_status": "all_ads",
      "contest_mode": false,
      "mod_reports": [],
      "author_patreon_flair": false,
      "author_flair_text_color": "dark",
      "permalink": "/r/xkcd/comments/cromff/video_of_serena_williams_knocking_down_a_drone/",
      "parent_whitelist_status": "all_ads",
      "stickied": false,
      "url": "https://www.facebook.com/pmouratoglou/videos/serenawilliams-special-drone-destruction-dd-advice-to-all-the-drones-dont-fly-ov/744037485973540/",
      "subreddit_subscribers": 123562,
      "created_utc": 1566060598,
      "discussion_type": null,
      "media": null,
      "is_video": false
    }
  },
  {
    "kind": "t3",
    "data": {
      "approved_at_utc": null,
      "subreddit": "xkcd",
      "selftext": "I guess I've been busy, must have missed the announcement about the new book, and man, do I feel out of the loop.  That said, I just preordered, and can NOT wait for the new book. Thing Explainer is one of the few books I keep on the display level of my book shelf.\n\n&amp;#x200B;\n\nI have a narrative question though. During the excerpt it says  \"They headed out to her practice court to see how effective the world’s best tennis player would be at fending off a robot invasion. \"  Is there a missing line or two from the excerpt where it's described that Novak Djokovic showed up?",
      "author_fullname": "t2_206jrtzx",
      "saved": false,
      "mod_reason_title": null,
      "gilded": 0,
      "clicked": false,
      "title": "Just discovered the new book, Pre-ordered! But I have a Q about the excerpt.",
      "link_flair_richtext": [],
      "subreddit_name_prefixed": "r/xkcd",
      "hidden": false,
      "pwls": 6,
      "link_flair_css_class": null,
      "downs": 0,
      "thumbnail_height": null,
      "hide_score": false,
      "name": "t3_csapdd",
      "quarantine": false,
      "link_flair_text_color": "dark",
      "author_flair_background_color": null,
      "subreddit_type": "public",
      "ups": 0,
      "total_awards_received": 0,
      "media_embed": {},
      "thumbnail_width": null,
      "author_flair_template_id": null,
      "is_original_content": false,
      "user_reports": [],
      "secure_media": null,
      "is_reddit_media_domain": false,
      "is_meta": false,
      "category": null,
      "secure_media_embed": {},
      "link_flair_text": null,
      "can_mod_post": false,
      "score": 0,
      "approved_by": null,
      "thumbnail": "self",
      "edited": false,
      "author_flair_css_class": null,
      "author_flair_richtext": [],
      "gildings": {},
      "content_categories": null,
      "is_self": true,
      "mod_note": null,
      "created": 1566209554,
      "link_flair_type": "text",
      "wls": 6,
      "banned_by": null,
      "author_flair_type": "text",
      "domain": "self.xkcd",
      "allow_live_comments": false,
      "selftext_html": "&lt;!-- SC_OFF --&gt;&lt;div class=\"md\"&gt;&lt;p&gt;I guess I&amp;#39;ve been busy, must have missed the announcement about the new book, and man, do I feel out of the loop.  That said, I just preordered, and can NOT wait for the new book. Thing Explainer is one of the few books I keep on the display level of my book shelf.&lt;/p&gt;\n\n&lt;p&gt;&amp;#x200B;&lt;/p&gt;\n\n&lt;p&gt;I have a narrative question though. During the excerpt it says  &amp;quot;They headed out to her practice court to see how effective the world’s best tennis player would be at fending off a robot invasion. &amp;quot;  Is there a missing line or two from the excerpt where it&amp;#39;s described that Novak Djokovic showed up?&lt;/p&gt;\n&lt;/div&gt;&lt;!-- SC_ON --&gt;",
      "likes": null,
      "suggested_sort": null,
      "banned_at_utc": null,
      "view_count": null,
      "archived": false,
      "no_follow": true,
      "is_crosspostable": false,
      "pinned": false,
      "over_18": false,
      "all_awardings": [],
      "media_only": false,
      "can_gild": false,
      "spoiler": false,
      "locked": false,
      "author_flair_text": null,
      "visited": false,
      "num_reports": null,
      "distinguished": null,
      "subreddit_id": "t5_2qh0z",
      "mod_reason_by": null,
      "removal_reason": null,
      "link_flair_background_color": "",
      "id": "csapdd",
      "is_robot_indexable": true,
      "report_reasons": null,
      "author": "Dunmurdering",
      "num_crossposts": 0,
      "num_comments": 4,
      "send_replies": true,
      "whitelist_status": "all_ads",
      "contest_mode": false,
      "mod_reports": [],
      "author_patreon_flair": false,
      "author_flair_text_color": null,
      "permalink": "/r/xkcd/comments/csapdd/just_discovered_the_new_book_preordered_but_i/",
      "parent_whitelist_status": "all_ads",
      "stickied": false,
      "url": "https://www.reddit.com/r/xkcd/comments/csapdd/just_discovered_the_new_book_preordered_but_i/",
      "subreddit_subscribers": 123562,
      "created_utc": 1566180754,
      "discussion_type": null,
      "media": null,
      "is_video": false
    }
  },
  {
    "kind": "t3",
    "data": {
      "approved_at_utc": null,
      "subreddit": "xkcd",
      "selftext": "I’ve been using XKCD: OS on IOS, but I’m switching to Android soon. Any good XKCD apps on there?",
      "author_fullname": "t2_xnz7o",
      "saved": false,
      "mod_reason_title": null,
      "gilded": 0,
      "clicked": false,
      "title": "Good XKCD app on Android?",
      "link_flair_richtext": [],
      "subreddit_name_prefixed": "r/xkcd",
      "hidden": false,
      "pwls": 6,
      "link_flair_css_class": null,
      "downs": 0,
      "thumbnail_height": null,
      "hide_score": false,
      "name": "t3_crwz7v",
      "quarantine": false,
      "link_flair_text_color": "dark",
      "author_flair_background_color": null,
      "subreddit_type": "public",
      "ups": 6,
      "total_awards_received": 0,
      "media_embed": {},
      "thumbnail_width": null,
      "author_flair_template_id": null,
      "is_original_content": false,
      "user_reports": [],
      "secure_media": null,
      "is_reddit_media_domain": false,
      "is_meta": false,
      "category": null,
      "secure_media_embed": {},
      "link_flair_text": null,
      "can_mod_post": false,
      "score": 6,
      "approved_by": null,
      "thumbnail": "self",
      "edited": false,
      "author_flair_css_class": null,
      "author_flair_richtext": [],
      "gildings": {},
      "content_categories": null,
      "is_self": true,
      "mod_note": null,
      "created": 1566132407,
      "link_flair_type": "text",
      "wls": 6,
      "banned_by": null,
      "author_flair_type": "text",
      "domain": "self.xkcd",
      "allow_live_comments": false,
      "selftext_html": "&lt;!-- SC_OFF --&gt;&lt;div class=\"md\"&gt;&lt;p&gt;I’ve been using XKCD: OS on IOS, but I’m switching to Android soon. Any good XKCD apps on there?&lt;/p&gt;\n&lt;/div&gt;&lt;!-- SC_ON --&gt;",
      "likes": null,
      "suggested_sort": null,
      "banned_at_utc": null,
      "view_count": null,
      "archived": false,
      "no_follow": true,
      "is_crosspostable": false,
      "pinned": false,
      "over_18": false,
      "all_awardings": [],
      "media_only": false,
      "can_gild": false,
      "spoiler": false,
      "locked": false,
      "author_flair_text": null,
      "visited": false,
      "num_reports": null,
      "distinguished": null,
      "subreddit_id": "t5_2qh0z",
      "mod_reason_by": null,
      "removal_reason": null,
      "link_flair_background_color": "",
      "id": "crwz7v",
      "is_robot_indexable": true,
      "report_reasons": null,
      "author": "Professor_Skywalker",
      "num_crossposts": 0,
      "num_comments": 4,
      "send_replies": true,
      "whitelist_status": "all_ads",
      "contest_mode": false,
      "mod_reports": [],
      "author_patreon_flair": false,
      "author_flair_text_color": null,
      "permalink": "/r/xkcd/comments/crwz7v/good_xkcd_app_on_android/",
      "parent_whitelist_status": "all_ads",
      "stickied": false,
      "url": "https://www.reddit.com/r/xkcd/comments/crwz7v/good_xkcd_app_on_android/",
      "subreddit_subscribers": 123562,
      "created_utc": 1566103607,
      "discussion_type": null,
      "media": null,
      "is_video": false
    }
  },
  {
    "kind": "t3",
    "data": {
      "approved_at_utc": null,
      "subreddit": "xkcd",
      "selftext": "",
      "author_fullname": "t2_kd9yk7",
      "saved": false,
      "mod_reason_title": null,
      "gilded": 0,
      "clicked": false,
      "title": "Someone important died but we're not sure how we feel about them",
      "link_flair_richtext": [],
      "subreddit_name_prefixed": "r/xkcd",
      "hidden": false,
      "pwls": 6,
      "link_flair_css_class": null,
      "downs": 0,
      "thumbnail_height": 140,
      "hide_score": false,
      "name": "t3_crd5po",
      "quarantine": false,
      "link_flair_text_color": "dark",
      "author_flair_background_color": null,
      "subreddit_type": "public",
      "ups": 722,
      "total_awards_received": 0,
      "media_embed": {},
      "thumbnail_width": 140,
      "author_flair_template_id": "a7b9097e-1f3f-11e4-a21b-12313b0b24aa",
      "is_original_content": false,
      "user_reports": [],
      "secure_media": null,
      "is_reddit_media_domain": false,
      "is_meta": false,
      "category": null,
      "secure_media_embed": {},
      "link_flair_text": null,
      "can_mod_post": false,
      "score": 722,
      "approved_by": null,
      "thumbnail": "https://a.thumbs.redditmedia.com/-dwLEx3A8MrtA_TRECjPnXS8vkEK1hy1PqkRqw78lU4.jpg",
      "edited": false,
      "author_flair_css_class": "doubleblack",
      "author_flair_richtext": [],
      "gildings": {},
      "post_hint": "image",
      "content_categories": null,
      "is_self": false,
      "mod_note": null,
      "created": 1566021496,
      "link_flair_type": "text",
      "wls": 6,
      "banned_by": null,
      "author_flair_type": "text",
      "domain": "media.discordapp.net",
      "allow_live_comments": false,
      "selftext_html": null,
      "likes": null,
      "suggested_sort": null,
      "banned_at_utc": null,
      "view_count": null,
      "archived": false,
      "no_follow": false,
      "is_crosspostable": false,
      "pinned": false,
      "over_18": false,
      "preview": {
        "images": [
          {
            "source": {
              "url": "https://external-preview.redd.it/e9nhWbGegJNi3qd0qcLX-tO-ztJ1vjTjuVeCLqDEs44.jpg?auto=webp&amp;s=fc5ac0c54a6beaab44daac60bd842ab801cef62a",
              "width": 2448,
              "height": 3264
            },
            "resolutions": [
              {
                "url": "https://external-preview.redd.it/e9nhWbGegJNi3qd0qcLX-tO-ztJ1vjTjuVeCLqDEs44.jpg?width=108&amp;crop=smart&amp;auto=webp&amp;s=b86f20aade4e365ee45bb13e9f0d7e0aefb66114",
                "width": 108,
                "height": 144
              },
              {
                "url": "https://external-preview.redd.it/e9nhWbGegJNi3qd0qcLX-tO-ztJ1vjTjuVeCLqDEs44.jpg?width=216&amp;crop=smart&amp;auto=webp&amp;s=70d00418bb0a833ead2c70d82f38804f7d0d6e11",
                "width": 216,
                "height": 288
              },
              {
                "url": "https://external-preview.redd.it/e9nhWbGegJNi3qd0qcLX-tO-ztJ1vjTjuVeCLqDEs44.jpg?width=320&amp;crop=smart&amp;auto=webp&amp;s=776b0d098da5adbc21f85426294158c6dcfcb47a",
                "width": 320,
                "height": 426
              },
              {
                "url": "https://external-preview.redd.it/e9nhWbGegJNi3qd0qcLX-tO-ztJ1vjTjuVeCLqDEs44.jpg?width=640&amp;crop=smart&amp;auto=webp&amp;s=a6c81a1b7be1dd655a64ee849f9a579c11b87f59",
                "width": 640,
                "height": 853
              },
              {
                "url": "https://external-preview.redd.it/e9nhWbGegJNi3qd0qcLX-tO-ztJ1vjTjuVeCLqDEs44.jpg?width=960&amp;crop=smart&amp;auto=webp&amp;s=a963c8dab3c8acc028cf184df619e2c9e2ca9ab7",
                "width": 960,
                "height": 1280
              },
              {
                "url": "https://external-preview.redd.it/e9nhWbGegJNi3qd0qcLX-tO-ztJ1vjTjuVeCLqDEs44.jpg?width=1080&amp;crop=smart&amp;auto=webp&amp;s=56a81d94d8091d5ccaf3fb6fa3fb2a352038bec6",
                "width": 1080,
                "height": 1440
              }
            ],
            "variants": {},
            "id": "rr19Ji414KsMRwCWPEC5yjIddMEmEr_jdMxh4qRA9Q8"
          }
        ],
        "enabled": true
      },
      "all_awardings": [],
      "media_only": false,
      "can_gild": false,
      "spoiler": false,
      "locked": false,
      "author_flair_text": "Double Blackhat :snoo_dealwithit:",
      "visited": false,
      "num_reports": null,
      "distinguished": null,
      "subreddit_id": "t5_2qh0z",
      "mod_reason_by": null,
      "removal_reason": null,
      "link_flair_background_color": "",
      "id": "crd5po",
      "is_robot_indexable": true,
      "report_reasons": null,
      "author": "Swaggerding",
      "num_crossposts": 0,
      "num_comments": 8,
      "send_replies": false,
      "whitelist_status": "all_ads",
      "contest_mode": false,
      "mod_reports": [],
      "author_patreon_flair": false,
      "author_flair_text_color": "dark",
      "permalink": "/r/xkcd/comments/crd5po/someone_important_died_but_were_not_sure_how_we/",
      "parent_whitelist_status": "all_ads",
      "stickied": false,
      "url": "https://media.discordapp.net/attachments/364924000029114370/612042137499992083/image0.jpg",
      "subreddit_subscribers": 123562,
      "created_utc": 1565992696,
      "discussion_type": null,
      "media": null,
      "is_video": false
    }
  }
]